{
  "id": "garantenpflicht",
  "titel": "Garantenpflicht",
  "inhalt": "redirect [Unterstützungspflicht#Garantenstellung im deutschen Strafrecht](unterstützungspflicht#garantenstellung-im-deutschen-strafrecht)",
  "struktur": [
    {
      "titel": "Einleitung",
      "inhalt": "redirect Unterstützungspflicht#Garantenstellung im deutschen Strafrecht",
      "tags": [
        "redirect",
        "unterstützungspflicht",
        "garantenstellung",
        "deutschen",
        "strafrecht"
      ]
    }
  ],
  "zusammenfassung": "redirect [Unterstützungspflicht#Garantenstellung im deutschen Strafrecht](unterstützungspflicht#garantenstellung-im-deutschen-strafrecht)...",
  "verwandteArtikel": [
    "unterstützungspflicht#garantenstellung-im-deutschen-strafrecht"
  ]
}