{
  "id": "verfahrensbeteiligte",
  "titel": "Verfahrensbeteiligte",
  "inhalt": "redirect [Betreuungsverfahren#Beteiligung_weiterer_Personen](betreuungsverfahren#beteiligung_weiterer_personen)\n\n[Kategorie:Betreuungsverfahren](kategorie:betreuungsverfahren)",
  "zusammenfassung": "redirect [Betreuungsverfahren#Beteiligung_weiterer_Personen](betreuungsverfahren#beteiligung_weiterer_personen)\n\n[Kategorie:Betreuungsverfahren](kategorie:betreuungsverfahren)...",
  "verwandteArtikel": [
    "betreuungsverfahren#beteiligung_weiterer_personen",
    "kategorie:betreuungsverfahren"
  ]
}